RodTracker/__init__.py
RodTracker/_version.py
RodTracker/backend/__init__.py
RodTracker/backend/detection.py
RodTracker/backend/file_locations.py
RodTracker/backend/img_data.py
RodTracker/backend/logger.py
RodTracker/backend/miscellaneous.py
RodTracker/backend/parallelism.py
RodTracker/backend/reconstruction.py
RodTracker/backend/rod_data.py
RodTracker/backend/settings.py
RodTracker/main.py
RodTracker/resources/example_data/calibrations/gp34.json
RodTracker/resources/example_data/calibrations/transformation.json
RodTracker/resources/example_data/csv/rods_df_black.csv
RodTracker/resources/example_data/csv/rods_df_blue.csv
RodTracker/resources/example_data/csv/rods_df_brown.csv
RodTracker/resources/example_data/csv/rods_df_green.csv
RodTracker/resources/example_data/csv/rods_df_orange.csv
RodTracker/resources/example_data/csv/rods_df_purple.csv
RodTracker/resources/example_data/csv/rods_df_red.csv
RodTracker/resources/example_data/csv/rods_df_yellow.csv
RodTracker/resources/example_data/images/gp3/0500.jpg
RodTracker/resources/example_data/images/gp3/0501.jpg
RodTracker/resources/example_data/images/gp3/0502.jpg
RodTracker/resources/example_data/images/gp3/0503.jpg
RodTracker/resources/example_data/images/gp3/0504.jpg
RodTracker/resources/example_data/images/gp3/0505.jpg
RodTracker/resources/example_data/images/gp3/0506.jpg
RodTracker/resources/example_data/images/gp3/0507.jpg
RodTracker/resources/example_data/images/gp3/0508.jpg
RodTracker/resources/example_data/images/gp3/0509.jpg
RodTracker/resources/example_data/images/gp3/0510.jpg
RodTracker/resources/example_data/images/gp3/0511.jpg
RodTracker/resources/example_data/images/gp3/0512.jpg
RodTracker/resources/example_data/images/gp3/0513.jpg
RodTracker/resources/example_data/images/gp3/0514.jpg
RodTracker/resources/example_data/images/gp3/0515.jpg
RodTracker/resources/example_data/images/gp3/0516.jpg
RodTracker/resources/example_data/images/gp3/0517.jpg
RodTracker/resources/example_data/images/gp3/0518.jpg
rodtracker-0.6.7.dist-info/LICENSE
rodtracker-0.6.7.dist-info/METADATA
rodtracker-0.6.7.dist-info/WHEEL
rodtracker-0.6.7.dist-info/entry_points.txt
rodtracker-0.6.7.dist-info/RECORD
