Metadata-Version: 2.3
Name: RodTracker
Version: 0.6.7
Summary: GUI to track rod-like particles on multiple cameras
License: GPL-3.0-only
Author: Adrian Niemann
Author-email: adrian.niemann@gmx.de
Requires-Python: >=3.8,<3.13
Classifier: Intended Audience :: Science/Research
Classifier: License :: OSI Approved :: GNU General Public License v3 (GPLv3)
Classifier: Operating System :: MacOS
Classifier: Operating System :: Microsoft :: Windows
Classifier: Operating System :: POSIX :: Linux
Classifier: Programming Language :: Python :: 3
Classifier: Programming Language :: Python :: 3.8
Classifier: Programming Language :: Python :: 3.9
Classifier: Programming Language :: Python :: 3.10
Classifier: Programming Language :: Python :: 3.11
Classifier: Programming Language :: Python :: 3.12
Classifier: Programming Language :: Python :: 3 :: Only
Classifier: Topic :: Scientific/Engineering :: Physics
Provides-Extra: build
Provides-Extra: dev
Provides-Extra: docs
Provides-Extra: test
Requires-Dist: ParticleDetection (>=0.4.3)
Requires-Dist: Pillow (>=10) ; extra == "dev"
Requires-Dist: PyQt3D (>=5.15.5)
Requires-Dist: PyQt5 (>=5.15.4)
Requires-Dist: PyQt5-stubs (>=5.15) ; extra == "dev"
Requires-Dist: Sphinx (>=7.1,<7.2) ; (python_version < "3.9") and (extra == "dev" or extra == "build" or extra == "docs")
Requires-Dist: Sphinx (>=7.2) ; (python_version >= "3.9") and (extra == "dev" or extra == "build" or extra == "docs")
Requires-Dist: docutils (>=0.18) ; extra == "dev" or extra == "build" or extra == "docs"
Requires-Dist: dunamai (>=1.18.0) ; extra == "dev" or extra == "build" or extra == "docs"
Requires-Dist: flake8 (>=5) ; extra == "dev"
Requires-Dist: importlib-resources (>=6.0,<7.0)
Requires-Dist: matplotlib (>=3.6.2) ; python_version >= "3.9"
Requires-Dist: matplotlib (>=3.6.2,<3.8) ; python_version < "3.9"
Requires-Dist: myst_parser (>=2) ; extra == "dev" or extra == "build" or extra == "docs"
Requires-Dist: numpy (>=1.21,<2) ; python_version >= "3.9"
Requires-Dist: numpy (>=1.21,<=1.25) ; python_version < "3.9"
Requires-Dist: pandas (>=1.2.5,<2.1) ; python_version < "3.9"
Requires-Dist: pandas (>=2.1.1) ; python_version >= "3.9"
Requires-Dist: platformdirs (>=3.2.0)
Requires-Dist: pyinstaller (>=6.0) ; extra == "dev" or extra == "build"
Requires-Dist: pytest (>=7.1.2) ; extra == "dev" or extra == "test"
Requires-Dist: pytest-cov (>=3.0.0) ; extra == "dev" or extra == "test"
Requires-Dist: pytest-qt (>=4.0.0) ; extra == "dev" or extra == "test"
Requires-Dist: qt5-applications (>=5.15) ; extra == "dev"
Requires-Dist: sphinx_rtd_theme (>=1.3) ; extra == "dev" or extra == "build" or extra == "docs"
Project-URL: Documentation, https://particletracking.readthedocs.io/
Project-URL: Repository, https://github.com/ANP-Granular/ParticleTracking
